topsisdarpan102003716/__init__.py
topsisdarpan102003716/topsis_darpan_102003716.py
topsisdarpan102003716-0.0.2.dist-info/METADATA
topsisdarpan102003716-0.0.2.dist-info/WHEEL
topsisdarpan102003716-0.0.2.dist-info/top_level.txt
topsisdarpan102003716-0.0.2.dist-info/RECORD
